{"rooster": ["cock.n.04"], "egg": ["egg.n.02"], "cup": ["cup.n.01"], "strawberry": ["strawberry.n.01"], "flower": ["flower.n.01"], "river": ["river.n.01"], "tree": ["tree.n.01"], "plate": ["plate.n.04"], "water": ["water.n.06"], "sea": ["sea.n.01"], "apple": ["apple.n.01"], "shirt": ["shirt.n.01"], "pork": ["pork.n.01"], "meat": ["meat.n.01"], "coffee": ["coffee.n.01"], "bicycle": ["bicycle.n.01"], "convertible": ["convertible.n.01"], "dog": ["dog.n.01"], "puppy": ["puppy.n.01"], "bed": ["bed.n.01"], "watermelon": ["watermelon.n.02"], "juice": ["juice.n.01"], "monkey": ["monkey.n.01"], "bush": ["shrub.n.01"], "vegetable": ["vegetable.n.01"], "shrimp": ["prawn.n.01"], "sauce": ["sauce.n.01"], "tomato": ["tomato.n.01"], "pepper": ["pepper.n.04"], "olive": ["olive.n.04"], "yogurt": ["yogurt.n.01"], "lake": ["lake.n.01"], "boat": ["boat.n.01"], "blonde": ["blond.n.01"], "beer": ["beer.n.01"], "restaurant": ["restaurant.n.01"], "noodle": ["noodle.n.01"], "carriage": ["passenger_car.n.01"], "donkey": ["domestic_ass.n.01"], "onion": ["onion.n.03"], "taco": ["taco.n.02"], "pizza": ["pizza.n.01"], "pond": ["pond.n.01"], "geranium": ["geranium.n.01"], "whale": ["whale.n.02"], "weed": ["weed.n.01"], "photographer": ["photographer.n.01"], "chair": ["chair.n.01"], "banana": ["banana.n.02"], "spoon": ["spoon.n.01"], "helicopter": ["helicopter.n.01"], "snack": ["bite.n.04"], "dumpling": ["dumpling.n.01"], "ruin": ["ruin.n.02"], "finger": ["finger.n.01"], "rice": ["rice.n.01"], "deer": ["deer.n.01"], "soldier": ["soldier.n.01"], "butterfly": ["butterfly.n.01"], "lion": ["lion.n.01"], "chef": ["chef.n.01"], "knife": ["knife.n.02"], "businessman": ["businessman.n.01"], "pen": ["pen.n.01"], "rose": ["rose.n.01"], "fork": ["fork.n.01"], "hotel": ["hotel.n.01"], "llama": ["llama.n.01"], "steak": ["steak.n.01"], "mushroom": ["mushroom.n.05"], "cabbage": ["cabbage.n.01"], "grape": ["grape.n.01"], "lego": ["lego.n.01"], "sled": ["sled.n.01"], "mouse": ["mouse.n.01"], "snake": ["snake.n.01"], "spectator": ["spectator.n.01"], "radio": ["radio_receiver.n.01"], "helmet": ["helmet.n.02"], "stork": ["stork.n.01"], "skeleton": ["skeletal_system.n.01"], "bread": ["bread.n.01"], "squirrel": ["squirrel.n.01"], "tank": ["tank_car.n.01"], "owl": ["owl.n.01"], "curry": ["curry.n.01"], "dessert": ["dessert.n.01"], "coat": ["coat.n.01"], "adult": ["adult.n.01"], "tiger": ["tiger.n.02"], "mask": ["mask.n.01"], "drum": ["drum.n.01"], "motorcycle": ["motorcycle.n.01"], "motorcyclist": ["motorcyclist.n.01"], "mosque": ["mosque.n.01"], "pedestrian": ["pedestrian.n.01"], "airplane": ["airplane.n.01"], "taxi": ["cab.n.03"], "soup": ["soup.n.01"], "turtle": ["turtle.n.02"], "ship": ["ship.n.01"], "pasta": ["pasta.n.01"], "scarf": ["scarf.n.01"], "cap": ["cap.n.01"], "insect": ["insect.n.01"], "sausage": ["sausage.n.01"], "salad": ["salad.n.01"], "pencil": ["pencil.n.01"], "papaya": ["papaya.n.02"], "skirt": ["skirt.n.02"], "blouse": ["blouse.n.01"], "trailer": ["trailer.n.04"], "grass": ["grass.n.01"], "tourist": ["tourist.n.01"], "lemon": ["lemon.n.01"], "phone": ["telephone.n.01"], "tie": ["necktie.n.01"], "seaplane": ["seaplane.n.01"], "cherry": ["cherry.n.03"], "fuchsia": ["fuchsia.n.01"], "hyena": ["hyena.n.01"], "waterfall": ["waterfall.n.01"], "stream": ["stream.n.01"], "jacket": ["jacket.n.01"], "piano": ["piano.n.01"], "guitar": ["guitar.n.01"], "cheese": ["cheese.n.01"], "bear": ["bear.n.01"], "stove": ["stove.n.01"], "wine": ["wine.n.01"], "hat": ["hat.n.01"], "zebra": ["zebra.n.01"], "arm": ["arm.n.01"], "seagull": ["gull.n.02"], "hospital": ["hospital.n.01"], "architecture": ["architecture.n.01"], "sandwich": ["sandwich.n.01"], "orange": ["orange.n.01"], "nail": ["nail.n.01"], "dough": ["dough.n.01"], "shed": ["shed.n.01"], "belt": ["belt.n.02"], "passenger": ["passenger.n.01"], "eye": ["eye.n.01"], "shark": ["shark.n.01"], "sailboat": ["sailboat.n.01"], "nut": ["nut.n.01"], "jean": ["jean.n.01"], "castle": ["palace.n.01"], "fillet": ["fillet.n.01"], "sushi": ["sushi.n.01"], "potato": ["potato.n.01"], "jeep": ["jeep.n.01"], "skin": ["skin.n.01"], "crane": ["crane.n.05"], "pumpkin": ["pumpkin.n.02"], "suv": ["sport_utility.n.01"], "lavender": ["lavender.n.01"], "lupine": ["lupine.n.01"], "uniform": ["uniform.n.01"], "starfish": ["starfish.n.01"], "wing": ["wing.n.01"], "fern": ["fern.n.01"], "elephant": ["elephant.n.01"], "mayonnaise": ["mayonnaise.n.01"], "rabbit": ["rabbit.n.01"], "kitten": ["kitten.n.01"], "dahlia": ["dahlia.n.01"], "bamboo": ["bamboo.n.02"], "pie": ["pie.n.01"], "salt": ["salt.n.02"], "suit": ["suit.n.01"], "lily": ["lily.n.01"], "pea": ["pea.n.01"], "invertebrate": ["invertebrate.n.01"], "mussel": ["mussel.n.01"], "donut": ["doughnut.n.02"], "puddle": ["pool.n.06"], "guy": ["guy.n.01"], "chalk": ["chalk.n.04"], "eagle": ["eagle.n.01"], "customer": ["customer.n.01"], "cafe": ["cafe.n.01"], "bee": ["bee.n.01"], "orchid": ["orchid.n.01"], "bacon": ["bacon.n.01"], "fisherman": ["fisherman.n.01"], "dandelion": ["dandelion.n.01"], "lap": ["lap.n.01"], "cucumber": ["cucumber.n.02"], "ham": ["ham.n.01"], "breakfast": ["breakfast.n.01"], "snowdrop": ["wood_anemone.n.01"], "pine": ["pine.n.01"], "neck": ["neck.n.01"], "sheep": ["sheep.n.01"], "pot": ["pot.n.01"], "passer": ["passerby.n.01"], "horse": ["horse.n.01"], "desk": ["desk.n.01"], "gun": ["gun.n.01"], "bulldog": ["bulldog.n.01"], "goat": ["goat.n.01"], "parrot": ["parrot.n.01"], "peacock": ["peacock.n.02"], "palm": ["palm.n.03"], "visitor": ["visitor.n.01"], "garage": ["garage.n.01"], "skyscraper": ["skyscraper.n.01"], "kettle": ["kettle.n.01"], "aircraft": ["aircraft.n.01"], "mandolin": ["mandolin.n.01"], "giraffe": ["giraffe.n.01"], "hood": ["hood.n.08"], "snail": ["snail.n.01"], "nose": ["nose.n.01"], "son": ["son.n.01"], "cyclist": ["cyclist.n.01"], "pant": ["trouser.n.01"], "sword": ["sword.n.01"], "seafood": ["seafood.n.01"], "yacht": ["yacht.n.01"], "lizard": ["lizard.n.01"], "theater": ["theater.n.01"], "pancake": ["pancake.n.01"], "forklift": ["forklift.n.01"], "dragonfly": ["dragonfly.n.01"], "teacher": ["teacher.n.01"], "coconut": ["coconut.n.02"], "doll": ["doll.n.01"], "bay": ["bay.n.01"], "dolphin": ["dolphinfish.n.02"], "fighter": ["fighter.n.02"], "jet": ["jet.n.01"], "butcher": ["butcher.n.03"], "carrot": ["carrot.n.03"], "spider": ["spider.n.01"], "monk": ["monk.n.01"], "peach": ["peach.n.03"], "kite": ["kite.n.03"], "turban": ["pillbox.n.01"], "doctor": ["doctor.n.01"], "beef": ["beef.n.02"], "necklace": ["necklace.n.01"], "sugar": ["sugar.n.01"], "top": ["top.n.10"], "greenhouse": ["greenhouse.n.01"], "antelope": ["antelope.n.01"], "cabin": ["cabin.n.02"], "chopstick": ["chopstick.n.01"], "accordion": ["accordion.n.01"], "wheat": ["wheat.n.01"], "pan": ["pan.n.01"], "grill": ["grillroom.n.01"], "persimmon": ["persimmon.n.02"], "hammer": ["hammer.n.02"], "skier": ["skier.n.01"], "bean": ["bean.n.01"], "camel": ["camel.n.01"], "iguana": ["common_iguana.n.01"], "sweater": ["sweater.n.01"], "swan": ["swan.n.01"], "policeman": ["policeman.n.01"], "canoe": ["canoe.n.01"], "raspberry": ["raspberry.n.02"], "ocean": ["ocean.n.01"], "gazebo": ["gazebo.n.01"], "lounger": ["recliner.n.01"], "vine": ["vine.n.01"], "reed": ["reed.n.01"], "motorbike": ["minibike.n.01"], "bun": ["bun.n.01"], "armchair": ["armchair.n.01"], "hiker": ["hiker.n.01"], "lime": ["lime.n.06"], "altar": ["altar.n.01"], "cookie": ["cookie.n.01"], "stool": ["stool.n.01"], "athlete": ["athlete.n.01"], "skateboard": ["skateboard.n.01"], "coffee_cup": ["coffee_cup.n.01"], "sports_car": ["sports_car.n.01"], "office_building": ["office_building.n.01"], "ice_cream": ["ice_cream.n.01"], "potato_chip": ["chip.n.04"], "racing_car": ["racer.n.02"], "computer_keyboard": ["computer_keyboard.n.01"], "dining_table": ["dining_table.n.01"], "fishing_boat": ["fishing_boat.n.01"], "tomato_sauce": ["tomato_sauce.n.01"], "apartment_building": ["apartment_building.n.01"], "cactus": ["cactus.n.01"], "cruise_ship": ["cruise_ship.n.01"], "pickup_truck": ["pickup.n.01"], "asparagus": ["asparagus.n.02"], "coconut_tree": ["coconut.n.03"], "side_dish": ["side_dish.n.01"], "fir_tree": ["fir.n.02"], "passenger_car": ["passenger_car.n.01"], "watch": ["watch.n.01"], "clock": ["clock.n.01"], "berry": ["berry.n.01"], "chocolate": ["chocolate.n.02"], "mountain": ["mountain.n.01"], "man": ["man.n.01"], "dancer": ["dancer.n.01"], "woman": ["woman.n.01"], "dish": ["dish.n.01", "dish.n.02"], "car": ["car.n.01"], "table": ["table.n.02"], "child": ["child.n.01"], "house": ["house.n.01"], "sky": ["sky.n.01"], "person": ["person.n.01"], "building": ["building.n.01"], "boy": ["male_child.n.01"], "hand": ["hand.n.01"], "cart": ["cart.n.01"], "fish": ["fish.n.01", "fish.n.02"], "couple": ["couple.n.01"], "corn": ["corn.n.03"], "tram": ["streetcar.n.01"], "girl": ["female_child.n.01"], "bird": ["bird.n.01", "bird.n.02"], "back": ["back.n.01"], "bull": ["bull.n.01"], "buffalo": ["american_bison.n.01"], "weapon": ["weapon.n.01"], "temple": ["temple.n.01"], "animal": ["animal.n.01"], "cat": ["domestic_cat.n.01"], "tea": ["tea.n.01"], "star": ["star.n.03"], "church": ["church.n.02"], "plant": ["plant.n.02"], "food": ["food.n.01"], "ferret": ["black-footed_ferret.n.01"], "leg": ["leg.n.01"], "chicken": ["chicken.n.01", "chicken.n.02"], "head": ["head.n.01"], "clothing": ["clothing.n.01"], "face": ["face.n.01"], "protester": ["dissenter.n.01"], "knee": ["knee.n.01"], "shoulder": ["shoulder.n.01"], "worker": ["worker.n.01"], "crab": ["crab.n.01"], "foot": ["foot.n.01"], "lady": ["lady.n.01"], "herb": ["herb.n.01", "herb.n.02"], "mouth": ["mouth.n.01"], "furniture": ["furniture.n.01"], "beak": ["beak.n.01"], "truck": ["truck.n.01"], "speaker": ["speaker.n.01"], "bench": ["bench.n.01"], "parsley": ["parsley.n.02"], "factory": ["factory.n.01"], "salmon": ["salmon.n.01", "salmon.n.03"], "duck": ["duck.n.01", "duck.n.03"], "mother": ["mother.n.01"], "dress": ["dress.n.01", "attire.n.01"], "milk": ["milk.n.01"], "tart": ["tart.n.03"], "costume": ["costume.n.01"], "baby": ["baby.n.01"], "participant": ["player.n.01"], "tractor": ["tractor.n.01"], "friend": ["friend.n.01"], "vehicle": ["vehicle.n.01"], "musician": ["musician.n.01"], "rider": ["rider.n.01"], "ear": ["ear.n.01"], "pastry": ["pastry.n.02"], "toy": ["plaything.n.01"], "cow": ["cow.n.01"], "student": ["student.n.01"], "scooter": ["motor_scooter.n.01"], "robe": ["robe.n.01"], "priest": ["priest.n.02"], "tail": ["tail.n.01"], "spaghetti": ["spaghetti.n.01"], "runner": ["runner.n.06"], "hen": ["hen.n.01"], "cathedral": ["cathedral.n.01"], "spinach": ["spinach.n.02"], "diver": ["diver.n.02"], "tooth": ["tooth.n.01"], "mansion": ["mansion.n.02"], "guard": ["guard.n.01"], "chest": ["thorax.n.02"], "father": ["father.n.01"], "counter": ["counter.n.01"], "vest": ["vest.n.01"], "couch": ["sofa.n.01"], "tableware": ["tableware.n.01"], "electronic_equipment": ["electronic_equipment.n.01"], "home_appliance": ["home_appliance.n.01"], "kitchen_utensil": ["kitchen_utensil.n.01"], "celestial_body": ["celestial_body.n.01"], "body_part": ["body_part.n.01"], "body_of_water": ["body_of_water.n.01"], "hand_tool": ["hand_tool.n.01"], "musical_instrument": ["musical_instrument.n.01"], "writing_implement": ["writing_implement.n.01"], "jewelry": ["jewelry.n.01"], "timepiece": ["timepiece.n.01"], "fruit": ["edible_fruit.n.01"], "lotus": ["lotus.n.01"], "clothes": ["apparel.n.01"], "bag": ["bag.n.01"], "backpack": ["backpack.n.01"], "sack": ["sack.n.01"], "pocket": ["pocket.n.01"]}